localconfig/__init__.py
localconfig/manager.py
localconfig/utils.py
localconfig-1.1.4.dist-info/LICENSE
localconfig-1.1.4.dist-info/METADATA
localconfig-1.1.4.dist-info/WHEEL
localconfig-1.1.4.dist-info/top_level.txt
localconfig-1.1.4.dist-info/RECORD
