Metadata-Version: 2.1
Name: localconfig
Version: 1.1.4
Summary: A simplified interface to ConfigParser using dot notion with data type / comment support.
Home-page: https://github.com/maxzheng/localconfig
Author: Max Zheng
Author-email: maxzheng.os @t gmail.com
License: MIT
Keywords: configuration config ConfigParser data type support
Classifier: Development Status :: 5 - Production/Stable
Classifier: Intended Audience :: Developers
Classifier: Topic :: Software Development
Classifier: License :: OSI Approved :: MIT License
Classifier: Programming Language :: Python :: 3
Classifier: Programming Language :: Python :: 3.6
Requires-Python: >=3.6
License-File: LICENSE
